{
  "id": "rap-da-felicidade",
  "title": "Rap da Felicidade",
  "folder": "Rap da Felicidade",
  "status": "ready",
  "musicxml": "scores/rap-da-felicidade.musicxml",
  "audio": "audio/rap-da-felicidade.wav",
  "fingeringsPdf": "fingerings/rap-da-felicidade-trompete-fingerings.pdf",
  "data": "data/songs/rap-da-felicidade.json",
  "defaultBpm": 100,
  "trumpetPart": "Trumpet in Bb Tpt. in Bb",
  "totalMeasures": 17,
  "totalBeats": 68.0,
  "notesCount": 88,
  "notes": [
    {
      "index": 0,
      "measure": 1,
      "beat": 1.0,
      "absBeat": 0.0,
      "durationBeats": 0.5,
      "written": "D4",
      "labelPt": "Re4",
      "fingering": [
        "1",
        "3"
      ],
      "tie": null
    },
    {
      "index": 1,
      "measure": 1,
      "beat": 1.5,
      "absBeat": 0.5,
      "durationBeats": 0.5,
      "written": "D4",
      "labelPt": "Re4",
      "fingering": [
        "1",
        "3"
      ],
      "tie": null
    },
    {
      "index": 2,
      "measure": 2,
      "beat": 1.0,
      "absBeat": 4.0,
      "durationBeats": 1.0,
      "written": "G4",
      "labelPt": "Sol4",
      "fingering": [
        "0"
      ],
      "tie": null
    },
    {
      "index": 3,
      "measure": 2,
      "beat": 2.0,
      "absBeat": 5.0,
      "durationBeats": 1.0,
      "written": "D4",
      "labelPt": "Re4",
      "fingering": [
        "1",
        "3"
      ],
      "tie": null
    },
    {
      "index": 4,
      "measure": 2,
      "beat": 3.0,
      "absBeat": 6.0,
      "durationBeats": 1.0,
      "written": "Eb4",
      "labelPt": "Mib4",
      "fingering": [
        "2",
        "3"
      ],
      "tie": null
    },
    {
      "index": 5,
      "measure": 2,
      "beat": 4.0,
      "absBeat": 7.0,
      "durationBeats": 0.5,
      "written": "D4",
      "labelPt": "Re4",
      "fingering": [
        "1",
        "3"
      ],
      "tie": null
    },
    {
      "index": 6,
      "measure": 2,
      "beat": 4.5,
      "absBeat": 7.5,
      "durationBeats": 0.5,
      "written": "C4",
      "labelPt": "Do4",
      "fingering": [
        "0"
      ],
      "tie": null
    },
    {
      "index": 7,
      "measure": 3,
      "beat": 2.5,
      "absBeat": 9.5,
      "durationBeats": 0.5,
      "written": "C4",
      "labelPt": "Do4",
      "fingering": [
        "0"
      ],
      "tie": null
    },
    {
      "index": 8,
      "measure": 3,
      "beat": 3.0,
      "absBeat": 10.0,
      "durationBeats": 0.5,
      "written": "C4",
      "labelPt": "Do4",
      "fingering": [
        "0"
      ],
      "tie": null
    },
    {
      "index": 9,
      "measure": 3,
      "beat": 3.5,
      "absBeat": 10.5,
      "durationBeats": 0.5,
      "written": "C4",
      "labelPt": "Do4",
      "fingering": [
        "0"
      ],
      "tie": null
    },
    {
      "index": 10,
      "measure": 3,
      "beat": 4.0,
      "absBeat": 11.0,
      "durationBeats": 0.5,
      "written": "D4",
      "labelPt": "Re4",
      "fingering": [
        "1",
        "3"
      ],
      "tie": null
    },
    {
      "index": 11,
      "measure": 3,
      "beat": 4.5,
      "absBeat": 11.5,
      "durationBeats": 0.5,
      "written": "Eb4",
      "labelPt": "Mib4",
      "fingering": [
        "2",
        "3"
      ],
      "tie": null
    },
    {
      "index": 12,
      "measure": 4,
      "beat": 1.0,
      "absBeat": 12.0,
      "durationBeats": 0.5,
      "written": "D4",
      "labelPt": "Re4",
      "fingering": [
        "1",
        "3"
      ],
      "tie": null
    },
    {
      "index": 13,
      "measure": 4,
      "beat": 1.5,
      "absBeat": 12.5,
      "durationBeats": 0.5,
      "written": "C4",
      "labelPt": "Do4",
      "fingering": [
        "0"
      ],
      "tie": null
    },
    {
      "index": 14,
      "measure": 4,
      "beat": 2.0,
      "absBeat": 13.0,
      "durationBeats": 0.5,
      "written": "D4",
      "labelPt": "Re4",
      "fingering": [
        "1",
        "3"
      ],
      "tie": null
    },
    {
      "index": 15,
      "measure": 4,
      "beat": 2.5,
      "absBeat": 13.5,
      "durationBeats": 0.5,
      "written": "Eb4",
      "labelPt": "Mib4",
      "fingering": [
        "2",
        "3"
      ],
      "tie": null
    },
    {
      "index": 16,
      "measure": 4,
      "beat": 3.0,
      "absBeat": 14.0,
      "durationBeats": 0.5,
      "written": "D4",
      "labelPt": "Re4",
      "fingering": [
        "1",
        "3"
      ],
      "tie": null
    },
    {
      "index": 17,
      "measure": 4,
      "beat": 3.5,
      "absBeat": 14.5,
      "durationBeats": 0.5,
      "written": "D4",
      "labelPt": "Re4",
      "fingering": [
        "1",
        "3"
      ],
      "tie": null
    },
    {
      "index": 18,
      "measure": 4,
      "beat": 4.0,
      "absBeat": 15.0,
      "durationBeats": 0.75,
      "written": "F4",
      "labelPt": "Fa4",
      "fingering": [
        "1"
      ],
      "tie": null
    },
    {
      "index": 19,
      "measure": 4,
      "beat": 4.75,
      "absBeat": 15.75,
      "durationBeats": 0.25,
      "written": "Eb4",
      "labelPt": "Mib4",
      "fingering": [
        "2",
        "3"
      ],
      "tie": "start"
    },
    {
      "index": 20,
      "measure": 5,
      "beat": 1.0,
      "absBeat": 16.0,
      "durationBeats": 0.5,
      "written": "Eb4",
      "labelPt": "Mib4",
      "fingering": [
        "2",
        "3"
      ],
      "tie": "stop"
    },
    {
      "index": 21,
      "measure": 5,
      "beat": 1.5,
      "absBeat": 16.5,
      "durationBeats": 0.5,
      "written": "D4",
      "labelPt": "Re4",
      "fingering": [
        "1",
        "3"
      ],
      "tie": null
    },
    {
      "index": 22,
      "measure": 5,
      "beat": 4.0,
      "absBeat": 19.0,
      "durationBeats": 0.5,
      "written": "D4",
      "labelPt": "Re4",
      "fingering": [
        "1",
        "3"
      ],
      "tie": null
    },
    {
      "index": 23,
      "measure": 5,
      "beat": 4.5,
      "absBeat": 19.5,
      "durationBeats": 0.5,
      "written": "D4",
      "labelPt": "Re4",
      "fingering": [
        "1",
        "3"
      ],
      "tie": null
    },
    {
      "index": 24,
      "measure": 6,
      "beat": 1.0,
      "absBeat": 20.0,
      "durationBeats": 1.0,
      "written": "Eb4",
      "labelPt": "Mib4",
      "fingering": [
        "2",
        "3"
      ],
      "tie": null
    },
    {
      "index": 25,
      "measure": 6,
      "beat": 2.0,
      "absBeat": 21.0,
      "durationBeats": 1.0,
      "written": "D4",
      "labelPt": "Re4",
      "fingering": [
        "1",
        "3"
      ],
      "tie": null
    },
    {
      "index": 26,
      "measure": 6,
      "beat": 3.0,
      "absBeat": 22.0,
      "durationBeats": 1.0,
      "written": "Eb4",
      "labelPt": "Mib4",
      "fingering": [
        "2",
        "3"
      ],
      "tie": null
    },
    {
      "index": 27,
      "measure": 6,
      "beat": 4.0,
      "absBeat": 23.0,
      "durationBeats": 0.5,
      "written": "D4",
      "labelPt": "Re4",
      "fingering": [
        "1",
        "3"
      ],
      "tie": null
    },
    {
      "index": 28,
      "measure": 6,
      "beat": 4.5,
      "absBeat": 23.5,
      "durationBeats": 0.5,
      "written": "C4",
      "labelPt": "Do4",
      "fingering": [
        "0"
      ],
      "tie": null
    },
    {
      "index": 29,
      "measure": 7,
      "beat": 2.5,
      "absBeat": 25.5,
      "durationBeats": 0.5,
      "written": "C4",
      "labelPt": "Do4",
      "fingering": [
        "0"
      ],
      "tie": null
    },
    {
      "index": 30,
      "measure": 7,
      "beat": 3.0,
      "absBeat": 26.0,
      "durationBeats": 0.5,
      "written": "C4",
      "labelPt": "Do4",
      "fingering": [
        "0"
      ],
      "tie": null
    },
    {
      "index": 31,
      "measure": 7,
      "beat": 3.5,
      "absBeat": 26.5,
      "durationBeats": 0.5,
      "written": "C4",
      "labelPt": "Do4",
      "fingering": [
        "0"
      ],
      "tie": null
    },
    {
      "index": 32,
      "measure": 7,
      "beat": 4.0,
      "absBeat": 27.0,
      "durationBeats": 0.5,
      "written": "D4",
      "labelPt": "Re4",
      "fingering": [
        "1",
        "3"
      ],
      "tie": null
    },
    {
      "index": 33,
      "measure": 7,
      "beat": 4.5,
      "absBeat": 27.5,
      "durationBeats": 0.5,
      "written": "Eb4",
      "labelPt": "Mib4",
      "fingering": [
        "2",
        "3"
      ],
      "tie": null
    },
    {
      "index": 34,
      "measure": 8,
      "beat": 1.0,
      "absBeat": 28.0,
      "durationBeats": 0.5,
      "written": "D4",
      "labelPt": "Re4",
      "fingering": [
        "1",
        "3"
      ],
      "tie": null
    },
    {
      "index": 35,
      "measure": 8,
      "beat": 1.5,
      "absBeat": 28.5,
      "durationBeats": 0.5,
      "written": "C4",
      "labelPt": "Do4",
      "fingering": [
        "0"
      ],
      "tie": null
    },
    {
      "index": 36,
      "measure": 8,
      "beat": 2.0,
      "absBeat": 29.0,
      "durationBeats": 0.5,
      "written": "D4",
      "labelPt": "Re4",
      "fingering": [
        "1",
        "3"
      ],
      "tie": null
    },
    {
      "index": 37,
      "measure": 8,
      "beat": 2.5,
      "absBeat": 29.5,
      "durationBeats": 0.5,
      "written": "Eb4",
      "labelPt": "Mib4",
      "fingering": [
        "2",
        "3"
      ],
      "tie": null
    },
    {
      "index": 38,
      "measure": 8,
      "beat": 3.0,
      "absBeat": 30.0,
      "durationBeats": 0.5,
      "written": "D4",
      "labelPt": "Re4",
      "fingering": [
        "1",
        "3"
      ],
      "tie": null
    },
    {
      "index": 39,
      "measure": 8,
      "beat": 3.5,
      "absBeat": 30.5,
      "durationBeats": 0.5,
      "written": "D4",
      "labelPt": "Re4",
      "fingering": [
        "1",
        "3"
      ],
      "tie": null
    },
    {
      "index": 40,
      "measure": 8,
      "beat": 4.0,
      "absBeat": 31.0,
      "durationBeats": 0.5,
      "written": "Bb3",
      "labelPt": "Sib3",
      "fingering": [
        "1"
      ],
      "tie": null
    },
    {
      "index": 41,
      "measure": 8,
      "beat": 4.5,
      "absBeat": 31.5,
      "durationBeats": 0.5,
      "written": "A3",
      "labelPt": "La3",
      "fingering": [
        "1",
        "2"
      ],
      "tie": null
    },
    {
      "index": 42,
      "measure": 9,
      "beat": 1.0,
      "absBeat": 32.0,
      "durationBeats": 1.0,
      "written": "G3",
      "labelPt": "Sol3",
      "fingering": [
        "1",
        "3"
      ],
      "tie": null
    },
    {
      "index": 43,
      "measure": 9,
      "beat": 2.5,
      "absBeat": 33.5,
      "durationBeats": 0.6667,
      "written": "D4",
      "labelPt": "Re4",
      "fingering": [
        "1",
        "3"
      ],
      "tie": null
    },
    {
      "index": 44,
      "measure": 9,
      "beat": 3.1667,
      "absBeat": 34.1667,
      "durationBeats": 0.6667,
      "written": "D4",
      "labelPt": "Re4",
      "fingering": [
        "1",
        "3"
      ],
      "tie": null
    },
    {
      "index": 45,
      "measure": 9,
      "beat": 3.8333,
      "absBeat": 34.8333,
      "durationBeats": 0.6667,
      "written": "D4",
      "labelPt": "Re4",
      "fingering": [
        "1",
        "3"
      ],
      "tie": null
    },
    {
      "index": 46,
      "measure": 9,
      "beat": 4.5,
      "absBeat": 35.5,
      "durationBeats": 0.5,
      "written": "G4",
      "labelPt": "Sol4",
      "fingering": [
        "0"
      ],
      "tie": "start"
    },
    {
      "index": 47,
      "measure": 10,
      "beat": 1.0,
      "absBeat": 36.0,
      "durationBeats": 1.0,
      "written": "G4",
      "labelPt": "Sol4",
      "fingering": [
        "0"
      ],
      "tie": "stop"
    },
    {
      "index": 48,
      "measure": 10,
      "beat": 2.0,
      "absBeat": 37.0,
      "durationBeats": 1.0,
      "written": "D4",
      "labelPt": "Re4",
      "fingering": [
        "1",
        "3"
      ],
      "tie": null
    },
    {
      "index": 49,
      "measure": 10,
      "beat": 3.0,
      "absBeat": 38.0,
      "durationBeats": 1.0,
      "written": "Eb4",
      "labelPt": "Mib4",
      "fingering": [
        "2",
        "3"
      ],
      "tie": null
    },
    {
      "index": 50,
      "measure": 10,
      "beat": 4.0,
      "absBeat": 39.0,
      "durationBeats": 0.5,
      "written": "D4",
      "labelPt": "Re4",
      "fingering": [
        "1",
        "3"
      ],
      "tie": null
    },
    {
      "index": 51,
      "measure": 10,
      "beat": 4.5,
      "absBeat": 39.5,
      "durationBeats": 0.5,
      "written": "C4",
      "labelPt": "Do4",
      "fingering": [
        "0"
      ],
      "tie": null
    },
    {
      "index": 52,
      "measure": 11,
      "beat": 1.5,
      "absBeat": 40.5,
      "durationBeats": 0.5,
      "written": "Eb4",
      "labelPt": "Mib4",
      "fingering": [
        "2",
        "3"
      ],
      "tie": null
    },
    {
      "index": 53,
      "measure": 11,
      "beat": 2.0,
      "absBeat": 41.0,
      "durationBeats": 0.5,
      "written": "C4",
      "labelPt": "Do4",
      "fingering": [
        "0"
      ],
      "tie": null
    },
    {
      "index": 54,
      "measure": 11,
      "beat": 3.0,
      "absBeat": 42.0,
      "durationBeats": 0.5,
      "written": "Eb4",
      "labelPt": "Mib4",
      "fingering": [
        "2",
        "3"
      ],
      "tie": null
    },
    {
      "index": 55,
      "measure": 11,
      "beat": 3.5,
      "absBeat": 42.5,
      "durationBeats": 0.5,
      "written": "C4",
      "labelPt": "Do4",
      "fingering": [
        "0"
      ],
      "tie": null
    },
    {
      "index": 56,
      "measure": 11,
      "beat": 4.5,
      "absBeat": 43.5,
      "durationBeats": 0.5,
      "written": "Eb4",
      "labelPt": "Mib4",
      "fingering": [
        "2",
        "3"
      ],
      "tie": null
    },
    {
      "index": 57,
      "measure": 12,
      "beat": 1.0,
      "absBeat": 44.0,
      "durationBeats": 0.5,
      "written": "C4",
      "labelPt": "Do4",
      "fingering": [
        "0"
      ],
      "tie": null
    },
    {
      "index": 58,
      "measure": 12,
      "beat": 2.0,
      "absBeat": 45.0,
      "durationBeats": 0.5,
      "written": "Eb4",
      "labelPt": "Mib4",
      "fingering": [
        "2",
        "3"
      ],
      "tie": null
    },
    {
      "index": 59,
      "measure": 12,
      "beat": 2.5,
      "absBeat": 45.5,
      "durationBeats": 0.5,
      "written": "C4",
      "labelPt": "Do4",
      "fingering": [
        "0"
      ],
      "tie": null
    },
    {
      "index": 60,
      "measure": 12,
      "beat": 3.5,
      "absBeat": 46.5,
      "durationBeats": 0.5,
      "written": "F4",
      "labelPt": "Fa4",
      "fingering": [
        "1"
      ],
      "tie": null
    },
    {
      "index": 61,
      "measure": 12,
      "beat": 4.0,
      "absBeat": 47.0,
      "durationBeats": 0.75,
      "written": "F4",
      "labelPt": "Fa4",
      "fingering": [
        "1"
      ],
      "tie": null
    },
    {
      "index": 62,
      "measure": 12,
      "beat": 4.75,
      "absBeat": 47.75,
      "durationBeats": 0.25,
      "written": "Eb4",
      "labelPt": "Mib4",
      "fingering": [
        "2",
        "3"
      ],
      "tie": "start"
    },
    {
      "index": 63,
      "measure": 13,
      "beat": 1.0,
      "absBeat": 48.0,
      "durationBeats": 0.5,
      "written": "Eb4",
      "labelPt": "Mib4",
      "fingering": [
        "2",
        "3"
      ],
      "tie": "stop"
    },
    {
      "index": 64,
      "measure": 13,
      "beat": 1.5,
      "absBeat": 48.5,
      "durationBeats": 0.5,
      "written": "D4",
      "labelPt": "Re4",
      "fingering": [
        "1",
        "3"
      ],
      "tie": null
    },
    {
      "index": 65,
      "measure": 13,
      "beat": 4.0,
      "absBeat": 51.0,
      "durationBeats": 0.5,
      "written": "D4",
      "labelPt": "Re4",
      "fingering": [
        "1",
        "3"
      ],
      "tie": null
    },
    {
      "index": 66,
      "measure": 13,
      "beat": 4.5,
      "absBeat": 51.5,
      "durationBeats": 0.5,
      "written": "D4",
      "labelPt": "Re4",
      "fingering": [
        "1",
        "3"
      ],
      "tie": null
    },
    {
      "index": 67,
      "measure": 14,
      "beat": 1.0,
      "absBeat": 52.0,
      "durationBeats": 1.0,
      "written": "Eb4",
      "labelPt": "Mib4",
      "fingering": [
        "2",
        "3"
      ],
      "tie": null
    },
    {
      "index": 68,
      "measure": 14,
      "beat": 2.0,
      "absBeat": 53.0,
      "durationBeats": 1.0,
      "written": "D4",
      "labelPt": "Re4",
      "fingering": [
        "1",
        "3"
      ],
      "tie": null
    },
    {
      "index": 69,
      "measure": 14,
      "beat": 3.0,
      "absBeat": 54.0,
      "durationBeats": 1.0,
      "written": "Eb4",
      "labelPt": "Mib4",
      "fingering": [
        "2",
        "3"
      ],
      "tie": null
    },
    {
      "index": 70,
      "measure": 14,
      "beat": 4.0,
      "absBeat": 55.0,
      "durationBeats": 0.5,
      "written": "D4",
      "labelPt": "Re4",
      "fingering": [
        "1",
        "3"
      ],
      "tie": null
    },
    {
      "index": 71,
      "measure": 14,
      "beat": 4.5,
      "absBeat": 55.5,
      "durationBeats": 0.5,
      "written": "C4",
      "labelPt": "Do4",
      "fingering": [
        "0"
      ],
      "tie": null
    },
    {
      "index": 72,
      "measure": 15,
      "beat": 2.5,
      "absBeat": 57.5,
      "durationBeats": 0.5,
      "written": "C4",
      "labelPt": "Do4",
      "fingering": [
        "0"
      ],
      "tie": null
    },
    {
      "index": 73,
      "measure": 15,
      "beat": 3.0,
      "absBeat": 58.0,
      "durationBeats": 0.5,
      "written": "C4",
      "labelPt": "Do4",
      "fingering": [
        "0"
      ],
      "tie": null
    },
    {
      "index": 74,
      "measure": 15,
      "beat": 3.5,
      "absBeat": 58.5,
      "durationBeats": 0.5,
      "written": "C4",
      "labelPt": "Do4",
      "fingering": [
        "0"
      ],
      "tie": null
    },
    {
      "index": 75,
      "measure": 15,
      "beat": 4.0,
      "absBeat": 59.0,
      "durationBeats": 0.5,
      "written": "D4",
      "labelPt": "Re4",
      "fingering": [
        "1",
        "3"
      ],
      "tie": null
    },
    {
      "index": 76,
      "measure": 15,
      "beat": 4.5,
      "absBeat": 59.5,
      "durationBeats": 0.5,
      "written": "Eb4",
      "labelPt": "Mib4",
      "fingering": [
        "2",
        "3"
      ],
      "tie": null
    },
    {
      "index": 77,
      "measure": 16,
      "beat": 1.0,
      "absBeat": 60.0,
      "durationBeats": 0.5,
      "written": "D4",
      "labelPt": "Re4",
      "fingering": [
        "1",
        "3"
      ],
      "tie": null
    },
    {
      "index": 78,
      "measure": 16,
      "beat": 1.5,
      "absBeat": 60.5,
      "durationBeats": 0.5,
      "written": "C4",
      "labelPt": "Do4",
      "fingering": [
        "0"
      ],
      "tie": null
    },
    {
      "index": 79,
      "measure": 16,
      "beat": 2.0,
      "absBeat": 61.0,
      "durationBeats": 0.5,
      "written": "D4",
      "labelPt": "Re4",
      "fingering": [
        "1",
        "3"
      ],
      "tie": null
    },
    {
      "index": 80,
      "measure": 16,
      "beat": 2.5,
      "absBeat": 61.5,
      "durationBeats": 0.5,
      "written": "Eb4",
      "labelPt": "Mib4",
      "fingering": [
        "2",
        "3"
      ],
      "tie": null
    },
    {
      "index": 81,
      "measure": 16,
      "beat": 3.0,
      "absBeat": 62.0,
      "durationBeats": 0.5,
      "written": "D4",
      "labelPt": "Re4",
      "fingering": [
        "1",
        "3"
      ],
      "tie": null
    },
    {
      "index": 82,
      "measure": 16,
      "beat": 3.5,
      "absBeat": 62.5,
      "durationBeats": 0.5,
      "written": "D4",
      "labelPt": "Re4",
      "fingering": [
        "1",
        "3"
      ],
      "tie": null
    },
    {
      "index": 83,
      "measure": 16,
      "beat": 4.0,
      "absBeat": 63.0,
      "durationBeats": 0.5,
      "written": "Bb3",
      "labelPt": "Sib3",
      "fingering": [
        "1"
      ],
      "tie": null
    },
    {
      "index": 84,
      "measure": 16,
      "beat": 4.5,
      "absBeat": 63.5,
      "durationBeats": 0.5,
      "written": "A3",
      "labelPt": "La3",
      "fingering": [
        "1",
        "2"
      ],
      "tie": null
    },
    {
      "index": 85,
      "measure": 17,
      "beat": 1.0,
      "absBeat": 64.0,
      "durationBeats": 1.0,
      "written": "G3",
      "labelPt": "Sol3",
      "fingering": [
        "1",
        "3"
      ],
      "tie": null
    },
    {
      "index": 86,
      "measure": 17,
      "beat": 4.0,
      "absBeat": 67.0,
      "durationBeats": 0.5,
      "written": "D4",
      "labelPt": "Re4",
      "fingering": [
        "1",
        "3"
      ],
      "tie": null
    },
    {
      "index": 87,
      "measure": 17,
      "beat": 4.5,
      "absBeat": 67.5,
      "durationBeats": 0.5,
      "written": "D4",
      "labelPt": "Re4",
      "fingering": [
        "1",
        "3"
      ],
      "tie": null
    }
  ]
}